cro_validate/__init__.py
cro_validate/api/__init__.py
cro_validate/api/configuration_api.py
cro_validate/api/definition_api.py
cro_validate/api/example_api.py
cro_validate/api/exception_api.py
cro_validate/api/name_resolver_api.py
cro_validate/classes/__init__.py
cro_validate/classes/configuration_classes.py
cro_validate/classes/definition_classes.py
cro_validate/classes/example_generator_classes.py
cro_validate/classes/exception_classes.py
cro_validate/classes/field_init_action_classes.py
cro_validate/classes/name_resolver_classes.py
cro_validate/classes/name_strategy_classes.py
cro_validate/classes/parameter_classes.py
cro_validate/classes/rule_classes.py
cro_validate/classes/schema_classes.py
cro_validate/classes/util_classes.py
cro_validate/enum/__init__.py
cro_validate/input/__init__.py
cro_validate/input/normalize_input.py
cro_validate/util/__init__.py
cro_validate/util/definition_util.py
cro_validate-0.0.40.dist-info/LICENSE
cro_validate-0.0.40.dist-info/METADATA
cro_validate-0.0.40.dist-info/WHEEL
cro_validate-0.0.40.dist-info/namespace_packages.txt
cro_validate-0.0.40.dist-info/top_level.txt
cro_validate-0.0.40.dist-info/zip-safe
cro_validate-0.0.40.dist-info/RECORD
