Metadata-Version: 2.1
Name: cro-validate
Version: 0.0.40
Summary: CRO Validation Library
Home-page: https://github.com/crosoftware/cro_validate
Author-email: develop@crosoftware.net
License: MIT
License-File: LICENSE
Provides-Extra: development
Requires-Dist: backlash ; extra == 'development'
Requires-Dist: waitress ; extra == 'development'
Requires-Dist: pudb ; extra == 'development'
Requires-Dist: ptpython ; extra == 'development'
Requires-Dist: ipython ; extra == 'development'
